{
  "id": "a0adfd79-62f4-4403-8670-b8db0964945b",
  "type": "din",
  "original_name": "video_pond1_20250911_175006.mp4",
  "timestamp": "2025-09-11T17:50:16.592466",
  "pond_number": 1,
  "total_larvae": 30000,
  "survival_rate": null,
  "text_content": "🦐 จำนวนกุ้งทั้งหมด: 3 ตัว\n✅ เคยขยับ: 0 ตัว (0.00%)\n📊 สถานะรวม: ❌ มีตัวนิ่งเยอะ\n\nid_1: sick\nid_2: sick\nid_3: sick\n",
  "output_video": "https://9f3933d1be32.ngrok-free.app/din/video_pond1_20250911_175013.mp4"
}